setup.cfg
setup.py
mongo_connector/__init__.py
mongo_connector/doc_managers/__init__.py
mongo_connector/doc_managers/algolia_doc_manager.py
mongo_doc_manager.egg-info/PKG-INFO
mongo_doc_manager.egg-info/SOURCES.txt
mongo_doc_manager.egg-info/dependency_links.txt
mongo_doc_manager.egg-info/pbr.json
mongo_doc_manager.egg-info/requires.txt
mongo_doc_manager.egg-info/top_level.txt