Metadata-Version: 1.1
Name: mongo-doc-manager
Version: 0.0.2
Summary: Algolia Mongo Connector
Home-page: https://github.com/10gen-labs/mongo-connector
Author: MongoDB, Inc.
Author-email: mz@menacommerce.com
License: http://www.apache.org/licenses/LICENSE-2.0.html
Keywords: mongo-connector,mongo,mongodb,algolia
Platform: any
Classifier: Development Status :: 4 - Beta
Classifier: Intended Audience :: Developers
Classifier: License :: OSI Approved :: Apache Software License
Classifier: Programming Language :: Python :: 2.6
Classifier: Programming Language :: Python :: 2.7
Classifier: Programming Language :: Python :: 3.3
Classifier: Programming Language :: Python :: 3.4
Classifier: Topic :: Database
Classifier: Topic :: Software Development :: Libraries :: Python Modules
Classifier: Operating System :: Unix
Classifier: Operating System :: MacOS :: MacOS X
Classifier: Operating System :: Microsoft :: Windows
Classifier: Operating System :: POSIX
